archstats/__init__.py
archstats/__main__.py
archstats/_version.py
archstats/archstats.py
archstats/db_backed.py
archstats/tests/__init__.py
archstats/tests/conftest.py
archstats/tests/sim_server.py
archstats/tests/test_basic.py
archstats/tests/json/getApplianceMetrics.json
archstats/tests/json/getApplianceMetricsForAppliance-pscaa01.json
archstats/tests/json/getApplianceMetricsForAppliance-pscaa02.json
archstats/tests/json/getCreationReportForAppliance-pscaa01.json
archstats/tests/json/getInstanceMetrics.json
archstats/tests/json/getProcessMetrics.json
archstats/tests/json/getProcessMetricsDataForAppliance-pscaa01.json
archstats/tests/json/getProcessMetricsDataForAppliance-pscaa02.json
archstats/tests/json/getStorageMetrics.json
archstats/tests/json/getStorageMetricsForAppliance-pscaa01.json
archstats/tests/json/getStorageMetricsForAppliance-pscaa02.json
archstats-0.0.1.dist-info/AUTHORS.rst
archstats-0.0.1.dist-info/LICENSE
archstats-0.0.1.dist-info/METADATA
archstats-0.0.1.dist-info/WHEEL
archstats-0.0.1.dist-info/entry_points.txt
archstats-0.0.1.dist-info/top_level.txt
archstats-0.0.1.dist-info/RECORD
