Metadata-Version: 2.1
Name: archstats
Version: 0.0.1
Summary: EPICS Archiver Appliance statistics IOC
Home-page: https://github.com/pcdshub/archstats
Author: SLAC National Accelerator Laboratory
Author-email: UNKNOWN
License: SLAC
Platform: UNKNOWN
Classifier: Development Status :: 2 - Pre-Alpha
Classifier: Natural Language :: English
Classifier: Programming Language :: Python :: 3
Requires-Dist: aiohttp[speedups]
Requires-Dist: caproto[standard] (>=0.7.0)
Requires-Dist: elasticsearch[async] (>=7.8.0)
Requires-Dist: inflection
Requires-Dist: versioneer
